logging_interceptor/__init__.py
logging_interceptor/loguru.py
logging_interceptor-0.1.2.dist-info/LICENSE
logging_interceptor-0.1.2.dist-info/METADATA
logging_interceptor-0.1.2.dist-info/WHEEL
logging_interceptor-0.1.2.dist-info/RECORD
