Metadata-Version: 2.1
Name: logging-interceptor
Version: 0.1.2
Summary: Intercept Python's standard logging and re-route the messages.
Home-page: https://github.com/imcf/logging-interceptor
Keywords: logging,loguru
Author: Matthew D. Scholefield
Author-email: matthew331199@gmail.com
Requires-Python: >=3.7.2,<4.0.0
Classifier: Programming Language :: Python :: 3
Classifier: Programming Language :: Python :: 3.8
Classifier: Programming Language :: Python :: 3.9
Classifier: Programming Language :: Python :: 3.10
Classifier: Programming Language :: Python :: 3.11
Requires-Dist: loguru (>=0.7.0,<0.8.0)
Project-URL: Repository, https://github.com/imcf/logging-interceptor
